[
  {
    "id": 1,
    "title": "2022 Polygon Trid Dirt Jump Mountain Bike",
    "rating": 4.7,
    "review": 144,
    "price": 1199,
    "img": "https://www.bikesonline.com/assets/thumbL/AITPX26TRD13G1.jpg?20210317031452&tr=w-316,h-226",
    "describe": "Light & durable hydroformed 6061 Aluminum frame with tapered headtube for more stiffness and short chainstays for precise handling."
  },
  {
    "id": 2,
    "title": "2022 Polygon Trid ZZ Slopestyle / Dirt Jump Bike",
    "rating": 4.7,
    "review": 80,
    "price": 1199,
    "img": "https://www.bikesonline.com/assets/thumbL/AITPX26TRZ13G1.jpg?20210506220007&tr=w-316,h-226",
    "describe": "Light & durable hydroformed 6061 Aluminum frame with tapered headtube for more stiffness and short chainstays for precise handling."
  },
  {
    "id": 3,
    "title": "2022 Polygon Siskiu T7 Dual Suspension Mountain Bike",
    "rating": 4.6,
    "review": 780,
    "price": 1299,
    "img": "https://www.bikesonline.com/assets/thumbL/4885599.jpg?20211124215314&tr=w-250,h-250",
    "describe": "Light & durable hydroformed 6061 Aluminum frame with tapered headtube for more stiffness and short chainstays for precise handling."
  },
  {
    "id": 4,
    "title": "2022 Polygon Siskiu D7 Dual Suspension Mountain Bike",
    "rating": 4.4,
    "review": 780,
    "price": 1799,
    "img": "https://www.bikesonline.com/assets/thumbL/SISKIU_D7_2022.jpg?20210714000215&tr=w-250,h-250",
    "describe": "Light & durable hydroformed 6061 Aluminum frame with tapered headtube for more stiffness and short chainstays for precise handling."
  },
  {
    "id": 5,
    "title": "2022 Polygon Siskiu T8 Dual Suspension Mountain Bike",
    "rating": 4.4,
    "review": 507,
    "price": 2499,
    "img": "https://www.bikesonline.com/assets/thumbL/4885111.jpg?20210317031545&tr=w-250,h-250",
    "describe": "Light & durable hydroformed 6061 Aluminum frame with tapered headtube for more stiffness and short chainstays for precise handling."
  },
  {
    "id": 6,
    "title": "2022 Polygon Siskiu D5 Dual Suspension Mountain Bike",
    "rating": 4.6,
    "review": 717,
    "price": 1099,
    "img": "https://www.bikesonline.com/assets/thumbL/SISKIU_D5_2022.jpg?20210713225156&tr=w-250,h-250",
    "describe": "Light & durable hydroformed 6061 Aluminum frame with tapered headtube for more stiffness and short chainstays for precise handling."
  },
  {
    "id": 7,
    "title": "2022 Polygon Xtrada 7 Hardtail Mountain Bike",
    "rating": 4.8,
    "review": 235,
    "price": 1399,
    "img": "https://www.bikesonline.com/assets/thumbL/XTRADA_7_22.jpg?20211004235448&tr=w-250,h-250",
    "describe": "Light & durable hydroformed 6061 Aluminum frame with tapered headtube for more stiffness and short chainstays for precise handling."
  },
  {
    "id": 8,
    "title": "2022 Polygon Xtrada 7 Hardtail Mountain Bike",
    "rating": 4.9,
    "review": 258,
    "price": 919,
    "img": "https://www.bikesonline.com/assets/thumbL/6489548.jpg?20210317031357&tr=w-250,h-250",
    "describe": "Light & durable hydroformed 6061 Aluminum frame with tapered headtube for more stiffness and short chainstays for precise handling."
  }
]
